movingpandas/__init__.py
movingpandas/geometry_utils.py
movingpandas/io.py
movingpandas/overlay.py
movingpandas/point_clusterer.py
movingpandas/spatiotemporal_utils.py
movingpandas/trajectory.py
movingpandas/trajectory_aggregator.py
movingpandas/trajectory_cleaner.py
movingpandas/trajectory_collection.py
movingpandas/trajectory_generalizer.py
movingpandas/trajectory_plotter.py
movingpandas/trajectory_smoother.py
movingpandas/trajectory_splitter.py
movingpandas/trajectory_stop_detector.py
movingpandas/trajectory_utils.py
movingpandas/unit_utils.py
movingpandas/tests/__init__.py
movingpandas/tests/test_geometry_utils.py
movingpandas/tests/test_io.py
movingpandas/tests/test_overlay.py
movingpandas/tests/test_point_clusterer.py
movingpandas/tests/test_show_versions.py
movingpandas/tests/test_trajectory.py
movingpandas/tests/test_trajectory_aggregator.py
movingpandas/tests/test_trajectory_cleaner.py
movingpandas/tests/test_trajectory_collection.py
movingpandas/tests/test_trajectory_generalizer.py
movingpandas/tests/test_trajectory_plotter.py
movingpandas/tests/test_trajectory_smoother.py
movingpandas/tests/test_trajectory_splitter.py
movingpandas/tests/test_trajectory_stop_detector.py
movingpandas/tools/_multi_threading.py
movingpandas/tools/_show_versions.py
movingpandas/tools/_warnings.py
movingpandas-0.22.3.dist-info/licenses/LICENSE.txt
movingpandas-0.22.3.dist-info/METADATA
movingpandas-0.22.3.dist-info/WHEEL
movingpandas-0.22.3.dist-info/top_level.txt
movingpandas-0.22.3.dist-info/RECORD
